{
    "default": {
      "colors": [
        {
          "label": "primary",
          "color": {
            "red": 139,
            "green": 170,
            "blue": 80,
            "alpha": 1
          },
          "hex": "#8baa50",
          "accessibility": {
            "luminance": 0.35,
            "luminancePercent": "35%",
            "recommendedTextColor": "#000000",
            "contrastRatio": 7.96,
            "wcagRating": "AAA"
          }
        },
        {
          "label": "secondary",
          "color": {
            "red": 111,
            "green": 149,
            "blue": 38,
            "alpha": 1
          },
          "hex": "#6f9526",
          "accessibility": {
            "luminance": 0.25,
            "luminancePercent": "25%",
            "recommendedTextColor": "#000000",
            "contrastRatio": 6,
            "wcagRating": "AA"
          }
        },
        {
          "label": "accent",
          "color": {
            "red": 38,
            "green": 171,
            "blue": 227,
            "alpha": 1
          },
          "hex": "#26ABE3",
          "accessibility": {
            "luminance": 0.35,
            "luminancePercent": "35%",
            "recommendedTextColor": "#000000",
            "contrastRatio": 8.02,
            "wcagRating": "AAA"
          }
        },
        {
          "label": "text",
          "color": {
            "red": 44,
            "green": 130,
            "blue": 166,
            "alpha": 1
          },
          "hex": "#2c82a6",
          "accessibility": {
            "luminance": 0.19,
            "luminancePercent": "19%",
            "recommendedTextColor": "#000000",
            "contrastRatio": 4.85,
            "wcagRating": "AA"
          }
        },
        {
          "label": "bg-1",
          "color": {
            "red": 255,
            "green": 255,
            "blue": 255,
            "alpha": 1
          },
          "hex": "#ffffff",
          "accessibility": {
            "luminance": 1,
            "luminancePercent": "100%",
            "recommendedTextColor": "#000000",
            "contrastRatio": 21,
            "wcagRating": "AAA"
          }
        },
        {
          "label": "bg-2",
          "color": {
            "red": 245,
            "green": 245,
            "blue": 245,
            "alpha": 1
          },
          "hex": "#f5f5f5",
          "accessibility": {
            "luminance": 0.91,
            "luminancePercent": "91%",
            "recommendedTextColor": "#000000",
            "contrastRatio": 19.26,
            "wcagRating": "AAA"
          }
        },
        {
          "label": "topbar-light",
          "color": {
            "red": 255,
            "green": 255,
            "blue": 255,
            "alpha": 1
          },
          "hex": "#ffffff",
          "accessibility": {
            "luminance": 1,
            "luminancePercent": "100%",
            "recommendedTextColor": "#000000",
            "contrastRatio": 21,
            "wcagRating": "AAA"
          }
        },
        {
          "label": "topbar-dark",
          "color": {
            "red": 111,
            "green": 149,
            "blue": 38,
            "alpha": 1
          },
          "hex": "#6f9526",
          "accessibility": {
            "luminance": 0.25,
            "luminancePercent": "25%",
            "recommendedTextColor": "#000000",
            "contrastRatio": 6,
            "wcagRating": "AA"
          }
        }
      ],
      "typography": [
        {
          "label": "font",
          "font": "'Nunito', helvetica, arial, sans-serif"
        },
        {
          "label": "font-title",
          "font": "'Nunito', sans-serif"
        }
      ],
      "logo_url": "data:image/svg+xml;utf8,%3Csvg%20xmlns%3D%22http%3A%2F%2Fwww.w3.org%2F2000%2Fsvg%22%20viewBox%3D%220%200%20134.16%2089.55%22%3E%3Cdefs%3E%3Cstyle%3E.aa7f93e3-4599-4073-899c-9afe02814a3a%7Bfill%3A%2394c733%3B%7D.a9782ce6-260b-4a23-8fdb-2ba4825385d4%2C.aa7f93e3-4599-4073-899c-9afe02814a3a%2C.adf12d9e-670b-42ff-8f7d-a0fd61f11d4e%2C.e082bc44-9ad4-4a9f-8f75-9026a3d0477d%7Bfill-rule%3Aevenodd%3B%7D.a9782ce6-260b-4a23-8fdb-2ba4825385d4%2C.ea8ed138-e3c2-4160-b88c-07105cecd7e6%7Bfill%3A%2326abe3%3B%7D.e082bc44-9ad4-4a9f-8f75-9026a3d0477d%7Bfill%3A%23666%3B%7D.adf12d9e-670b-42ff-8f7d-a0fd61f11d4e%7Bfill%3A%23999%3B%7D%3C%2Fstyle%3E%3C%2Fdefs%3E%3Ctitle%3EAsset%201%3C%2Ftitle%3E%3Cg%20id%3D%22ba84c701-6180-414b-a422-3722361fd72e%22%20data-name%3D%22Layer%202%22%3E%3Cg%20id%3D%22f6ea7a7b-1324-4a44-ab70-4b1fa51b7901%22%20data-name%3D%22Layer%201%22%3E%3Cpath%20class%3D%22aa7f93e3-4599-4073-899c-9afe02814a3a%22%20d%3D%22M13.29%2C43.2c50.78-19.43%2C60%2C8.61%2C106.28-5.61C79.32%2C60.84%2C66.16%2C31.59%2C13.29%2C43.2Z%22%20style%3D%22fill%3A%20rgb(148%2C%20199%2C%2051)%20!important%3B%22%2F%3E%3Cpath%20class%3D%22a9782ce6-260b-4a23-8fdb-2ba4825385d4%22%20d%3D%22M119.16%2C39.51c-49.41%2C37.87-54%2C4.43-89.59%2C3.71C67.69%2C37.22%2C69%2C65.22%2C119.16%2C39.51Z%22%20style%3D%22fill%3A%20rgb(38%2C%20171%2C%20227)%20!important%3B%22%2F%3E%3Cpolygon%20class%3D%22e082bc44-9ad4-4a9f-8f75-9026a3d0477d%22%20points%3D%2245.43%2022.31%2022.38%2036.9%2046.63%2012.85%2053.55%2020.26%2048.86%2025.31%2045.43%2022.31%22%20style%3D%22fill%3A%20rgb(102%2C%20102%2C%20102)%20!important%3B%22%2F%3E%3Cpolygon%20class%3D%22e082bc44-9ad4-4a9f-8f75-9026a3d0477d%22%20points%3D%2293.69%2022.2%2091.25%2024.3%2087.06%2018.75%2093.49%2012.85%20115.67%2038.58%2093.69%2022.2%22%20style%3D%22fill%3A%20rgb(102%2C%20102%2C%20102)%20!important%3B%22%2F%3E%3Cpolygon%20class%3D%22e082bc44-9ad4-4a9f-8f75-9026a3d0477d%22%20points%3D%2271.88%2011.16%2042.65%2035.27%2072.22%200%2099.28%2037.78%2071.88%2011.16%22%20style%3D%22fill%3A%20rgb(102%2C%20102%2C%20102)%20!important%3B%22%2F%3E%3Cpolygon%20class%3D%22adf12d9e-670b-42ff-8f7d-a0fd61f11d4e%22%20points%3D%2257.17%2025.71%2071.07%2014.07%2082.11%2025.85%2073.16%2020.32%2070.41%2029%2068.54%2020.16%2057.17%2025.71%22%20style%3D%22fill%3A%20rgb(153%2C%20153%2C%20153)%20!important%3B%22%2F%3E%3Cpath%20class%3D%22ea8ed138-e3c2-4160-b88c-07105cecd7e6%22%20d%3D%22M9.63%2C84.75a3.57%2C3.57%2C0%2C0%2C0-.25-1.29%2C3.16%2C3.16%2C0%2C0%2C0-.71-1.09%2C3.25%2C3.25%2C0%2C0%2C0-2.31-1%2C3.36%2C3.36%2C0%2C0%2C0-1.25.25%2C3.37%2C3.37%2C0%2C0%2C0-1.77%2C1.81%2C3.58%2C3.58%2C0%2C0%2C0-.25%2C1.3A3.51%2C3.51%2C0%2C0%2C0%2C3.34%2C86a3.16%2C3.16%2C0%2C0%2C0%2C.71%2C1.09%2C3.21%2C3.21%2C0%2C0%2C0%2C1.06.72%2C3.28%2C3.28%2C0%2C0%2C0%2C2.5%2C0%2C3.21%2C3.21%2C0%2C0%2C0%2C1.06-.72%2C3.41%2C3.41%2C0%2C0%2C0%2C1-2.37Zm1.52%2C0a4.45%2C4.45%2C0%2C0%2C1-.36%2C1.8%2C4.67%2C4.67%2C0%2C0%2C1-1%2C1.52%2C5.33%2C5.33%2C0%2C0%2C1-1.56%2C1%2C4.59%2C4.59%2C0%2C0%2C1-1.83.35A4.76%2C4.76%2C0%2C0%2C1%2C3%2C88.05a4.63%2C4.63%2C0%2C0%2C1-1-1.51%2C4.82%2C4.82%2C0%2C0%2C1%2C0-3.62A4.57%2C4.57%2C0%2C0%2C1%2C3%2C81.4a4.8%2C4.8%2C0%2C0%2C1%2C1.55-1%2C5.05%2C5.05%2C0%2C0%2C1%2C1.84-.35%2C5%2C5%2C0%2C0%2C1%2C1.83.35%2C4.84%2C4.84%2C0%2C0%2C1%2C1.56%2C1%2C4.71%2C4.71%2C0%2C0%2C1%2C1%2C1.53%2C4.63%2C4.63%2C0%2C0%2C1%2C.36%2C1.8Zm6-.68h.26a2.87%2C2.87%2C0%2C0%2C0%2C1.53-.27%2C1.06%2C1.06%2C0%2C0%2C0%2C.38-1%2C1.21%2C1.21%2C0%2C0%2C0-.4-1%2C2.65%2C2.65%2C0%2C0%2C0-1.51-.31H17.1v2.57ZM17%2C85.2v4H15.64v-9h2a7.18%2C7.18%2C0%2C0%2C1%2C1.39.11%2C2.23%2C2.23%2C0%2C0%2C1%2C.84.39%2C2%2C2%2C0%2C0%2C1%2C.64.84%2C2.68%2C2.68%2C0%2C0%2C1%2C.23%2C1.12%2C2.49%2C2.49%2C0%2C0%2C1-.52%2C1.68%2C2.31%2C2.31%2C0%2C0%2C1-1.54.73l3.08%2C4.08H20.12l-3-4Zm11.42-3.71v7.72H27V81.49H24.59V80.26h6.2v1.23Zm6.31%2C7.72V80.26h1.45v3.35h4.4v-3.3h1.46v9H40.59V84.91h-4.4v4.35Zm19.85-4.46a3.37%2C3.37%2C0%2C0%2C0-.25-1.29%2C3.3%2C3.3%2C0%2C0%2C0-1.75-1.81%2C3.23%2C3.23%2C0%2C0%2C0-1.26-.26%2C3.41%2C3.41%2C0%2C0%2C0-1.26.25%2C3.24%2C3.24%2C0%2C0%2C0-1.06.73%2C3.55%2C3.55%2C0%2C0%2C0-.71%2C1.08%2C3.61%2C3.61%2C0%2C0%2C0-.24%2C1.3A3.33%2C3.33%2C0%2C0%2C0%2C49%2C87.12a3.19%2C3.19%2C0%2C0%2C0%2C2.32%2C1%2C3.09%2C3.09%2C0%2C0%2C0%2C1.24-.25%2C3.21%2C3.21%2C0%2C0%2C0%2C1.06-.72%2C3.41%2C3.41%2C0%2C0%2C0%2C1-2.37Zm1.52%2C0a4.45%2C4.45%2C0%2C0%2C1-.36%2C1.8%2C4.57%2C4.57%2C0%2C0%2C1-1%2C1.52%2C4.84%2C4.84%2C0%2C0%2C1-1.56%2C1%2C4.57%2C4.57%2C0%2C0%2C1-1.82.35%2C4.67%2C4.67%2C0%2C0%2C1-1.84-.35%2C4.8%2C4.8%2C0%2C0%2C1-1.55-1%2C4.53%2C4.53%2C0%2C0%2C1-1-1.51%2C4.73%2C4.73%2C0%2C0%2C1%2C0-3.62%2C4.28%2C4.28%2C0%2C0%2C1%2C1-1.52%2C4.4%2C4.4%2C0%2C0%2C1%2C1.55-1%2C5%2C5%2C0%2C0%2C1%2C3.67%2C0A4.73%2C4.73%2C0%2C0%2C1%2C55.79%2C83a4.63%2C4.63%2C0%2C0%2C1%2C.36%2C1.8Zm6%2C3.14h1.23a6.38%2C6.38%2C0%2C0%2C0%2C1.51-.13%2C2.3%2C2.3%2C0%2C0%2C0%2C.88-.45%2C2.66%2C2.66%2C0%2C0%2C0%2C.76-1.08%2C4.67%2C4.67%2C0%2C0%2C0%2C0-3%2C2.66%2C2.66%2C0%2C0%2C0-.76-1.08%2C2.43%2C2.43%2C0%2C0%2C0-.91-.45%2C7.11%2C7.11%2C0%2C0%2C0-1.66-.13h-1V87.9Zm-1.45%2C1.32V80.26h2a12.78%2C12.78%2C0%2C0%2C1%2C2.69.19%2C3.66%2C3.66%2C0%2C0%2C1%2C1.37.64%2C3.77%2C3.77%2C0%2C0%2C1%2C1.18%2C1.53%2C5.83%2C5.83%2C0%2C0%2C1%2C0%2C4.23%2C3.82%2C3.82%2C0%2C0%2C1-1.18%2C1.52%2C3.69%2C3.69%2C0%2C0%2C1-1.34.64%2C10.15%2C10.15%2C0%2C0%2C1-2.33.2H60.66Zm19.76-4.46a3.57%2C3.57%2C0%2C0%2C0-.25-1.29%2C3.16%2C3.16%2C0%2C0%2C0-.71-1.09%2C3.25%2C3.25%2C0%2C0%2C0-2.31-1%2C3.37%2C3.37%2C0%2C0%2C0-1.27%2C6.45%2C3.22%2C3.22%2C0%2C0%2C0%2C1.26.25%2C3.14%2C3.14%2C0%2C0%2C0%2C1.25-.25%2C3.21%2C3.21%2C0%2C0%2C0%2C1.06-.72%2C3.41%2C3.41%2C0%2C0%2C0%2C1-2.37Zm1.51%2C0a4.81%2C4.81%2C0%2C0%2C1-.35%2C1.8%2C4.56%2C4.56%2C0%2C0%2C1-1%2C1.52%2C4.84%2C4.84%2C0%2C0%2C1-1.56%2C1%2C4.57%2C4.57%2C0%2C0%2C1-1.82.35%2C4.76%2C4.76%2C0%2C0%2C1-3.39-1.37%2C4.63%2C4.63%2C0%2C0%2C1-1-1.51%2C4.82%2C4.82%2C0%2C0%2C1%2C0-3.62%2C4.57%2C4.57%2C0%2C0%2C1%2C1-1.52%2C4.8%2C4.8%2C0%2C0%2C1%2C1.55-1%2C5.05%2C5.05%2C0%2C0%2C1%2C1.84-.35A5%2C5%2C0%2C0%2C1%2C79%2C80.4a4.4%2C4.4%2C0%2C0%2C1%2C1.55%2C1%2C4.5%2C4.5%2C0%2C0%2C1%2C1%2C1.53%2C4.81%2C4.81%2C0%2C0%2C1%2C.35%2C1.8Zm4.5%2C4.46V79.9l5.69%2C5.47.47.5c.16.17.32.37.5.59v-6.2h1.34v9.29L88.63%2C84c-.15-.15-.3-.3-.45-.47a5.34%2C5.34%2C0%2C0%2C1-.41-.53v6.23Zm15.78-7.72v7.72h-1.45V81.49H98.38V80.26h6.2v1.23Zm6.22%2C7.72V80.26h1.46v8.95ZM122%2C82.43a4.53%2C4.53%2C0%2C0%2C0-1.3-.79%2C4.18%2C4.18%2C0%2C0%2C0-1.45-.26%2C3.17%2C3.17%2C0%2C0%2C0-2.38.94%2C3.67%2C3.67%2C0%2C0%2C0%2C0%2C4.83%2C3%2C3%2C0%2C0%2C0%2C2.26.94%2C3.89%2C3.89%2C0%2C0%2C0%2C1.51-.28A4.68%2C4.68%2C0%2C0%2C0%2C122%2C87v1.65a4.36%2C4.36%2C0%2C0%2C1-1.28.63%2C5%2C5%2C0%2C0%2C1-1.49.2%2C5.14%2C5.14%2C0%2C0%2C1-1.9-.33%2C4.71%2C4.71%2C0%2C0%2C1-1.53-1%2C4.57%2C4.57%2C0%2C0%2C1-1-1.52%2C5%2C5%2C0%2C0%2C1%2C0-3.7%2C4.57%2C4.57%2C0%2C0%2C1%2C2.55-2.52%2C4.91%2C4.91%2C0%2C0%2C1%2C1.86-.34%2C5.17%2C5.17%2C0%2C0%2C1%2C1.51.23%2C5.1%2C5.1%2C0%2C0%2C1%2C1.38.69L122%2C82.42Zm4.12%2C5%2C1.16-.53a1.72%2C1.72%2C0%2C0%2C0%2C.61.91%2C1.85%2C1.85%2C0%2C0%2C0%2C1.12.31%2C1.47%2C1.47%2C0%2C0%2C0%2C1-.36%2C1.25%2C1.25%2C0%2C0%2C0%2C.38-1c0-.53-.44-1-1.31-1.41l-.28-.13a6.19%2C6.19%2C0%2C0%2C1-2-1.31%2C2.16%2C2.16%2C0%2C0%2C1-.5-1.42%2C2.31%2C2.31%2C0%2C0%2C1%2C.75-1.78A2.77%2C2.77%2C0%2C0%2C1%2C129%2C80a3.2%2C3.2%2C0%2C0%2C1%2C1.66.39%2C2%2C2%2C0%2C0%2C1%2C.92%2C1.09l-1.13.59a1.94%2C1.94%2C0%2C0%2C0-.59-.62%2C1.57%2C1.57%2C0%2C0%2C0-1.67.11%2C1.07%2C1.07%2C0%2C0%2C0-.35.82c0%2C.54.51%2C1%2C1.52%2C1.51l.18.08a5.39%2C5.39%2C0%2C0%2C1%2C1.82%2C1.2%2C2.16%2C2.16%2C0%2C0%2C1%2C.5%2C1.46%2C2.63%2C2.63%2C0%2C0%2C1-.8%2C2%2C3.58%2C3.58%2C0%2C0%2C1-4%2C.22%2C2.49%2C2.49%2C0%2C0%2C1-1-1.51Z%22%20style%3D%22fill%3A%20rgb(38%2C%20171%2C%20227)%20!important%3B%22%2F%3E%3Cpath%20d%3D%22M2%2C70v3.09a8.4%2C8.4%2C0%2C0%2C1-.07%2C1%2C4.54%2C4.54%2C0%2C0%2C1-.09.51%2C1%2C1%2C0%2C0%2C1-.17.37.46.46%2C0%2C0%2C1-.3.19H1a2.67%2C2.67%2C0%2C0%2C1-.4%2C0%2C.49.49%2C0%2C0%2C0-.24%2C0%2C.12.12%2C0%2C0%2C0-.07.11.15.15%2C0%2C0%2C0%2C.1.15.71.71%2C0%2C0%2C0%2C.29%2C0H5.87a.71.71%2C0%2C0%2C0%2C.29%2C0%2C.15.15%2C0%2C0%2C0%2C.1-.15.1.1%2C0%2C0%2C0-.06-.11.28.28%2C0%2C0%2C0-.18%2C0H5.07A.8.8%2C0%2C0%2C1%2C4.63%2C75a1%2C1%2C0%2C0%2C1-.2-.36%2C2.28%2C2.28%2C0%2C0%2C1-.09-.51c0-.27-.06-.62-.07-1s0-.89%2C0-1.41v-2a.15.15%2C0%2C0%2C1%2C0-.13.24.24%2C0%2C0%2C1%2C.12%2C0H6.26a.38.38%2C0%2C0%2C1%2C.16.12%2C2.88%2C2.88%2C0%2C0%2C1%2C.3.39l.47.65c.17.26.36.53.56.81l.59.82c.36.5.69.94%2C1%2C1.31a9.49%2C9.49%2C0%2C0%2C0%2C.85.94%2C4.06%2C4.06%2C0%2C0%2C0%2C.82.61%2C2.57%2C2.57%2C0%2C0%2C0%2C.52.21%2C3.55%2C3.55%2C0%2C0%2C0%2C.65.12h3a.15.15%2C0%2C0%2C0%2C.1-.16.1.1%2C0%2C0%2C0-.06-.11.25.25%2C0%2C0%2C0-.17%2C0h-.55l-.31-.07a4.78%2C4.78%2C0%2C0%2C1-.48-.19%2C4%2C4%2C0%2C0%2C1-.62-.39%2C5.36%2C5.36%2C0%2C0%2C1-.76-.67c-.57-.61-1.2-1.33-1.88-2.19S9%2C69.93%2C8.14%2C68.85a10.06%2C10.06%2C0%2C0%2C0%2C1.54-1.52%2C4.71%2C4.71%2C0%2C0%2C0%2C.79-1.42%2C4.21%2C4.21%2C0%2C0%2C0%2C.23-1.41%2C2.79%2C2.79%2C0%2C0%2C0-.13-.91%2C3.48%2C3.48%2C0%2C0%2C0-.32-.77%2C3.56%2C3.56%2C0%2C0%2C0-.43-.59%2C3.31%2C3.31%2C0%2C0%2C0-.44-.39%2C4.11%2C4.11%2C0%2C0%2C0-1.12-.53%2C6.19%2C6.19%2C0%2C0%2C0-1.21-.25A10.29%2C10.29%2C0%2C0%2C0%2C5.81%2C61H.43a.86.86%2C0%2C0%2C0-.32%2C0%2C.13.13%2C0%2C0%2C0-.11.14.13.13%2C0%2C0%2C0%2C.09.14H.76l.33.05a1.18%2C1.18%2C0%2C0%2C1%2C.49.2.64.64%2C0%2C0%2C1%2C.25.35%2C1.71%2C1.71%2C0%2C0%2C1%2C.09.55V70Zm2.29-7.78a.28.28%2C0%2C0%2C1%2C0-.18A.19.19%2C0%2C0%2C1%2C4.39%2C62a1.39%2C1.39%2C0%2C0%2C1%2C.4-.06h.62a2.71%2C2.71%2C0%2C0%2C1%2C.75.1%2C2.83%2C2.83%2C0%2C0%2C1%2C.79.36%2C2.63%2C2.63%2C0%2C0%2C1%2C.72.65%2C3.16%2C3.16%2C0%2C0%2C1%2C.51%2C1%2C4.62%2C4.62%2C0%2C0%2C1%2C.2%2C1.43%2C4.9%2C4.9%2C0%2C0%2C1-.17%2C1.37%2C3%2C3%2C0%2C0%2C1-.42%2C1%2C2.21%2C2.21%2C0%2C0%2C1-.55.59%2C2.33%2C2.33%2C0%2C0%2C1-.34.2%2C1.43%2C1.43%2C0%2C0%2C1-.42.1c-.21%2C0-.41%2C0-.62%2C0H5.35l-.51-.06a3.69%2C3.69%2C0%2C0%2C1-.45-.11.24.24%2C0%2C0%2C1-.14-.12.45.45%2C0%2C0%2C1%2C0-.23v-5.9Zm12%2C8.61v2.71a3.79%2C3.79%2C0%2C0%2C1-.06.88%2C1.32%2C1.32%2C0%2C0%2C1-.14.55.52.52%2C0%2C0%2C1-.36.25h-.6a.41.41%2C0%2C0%2C0-.22%2C0%2C.16.16%2C0%2C0%2C0-.06.12.16.16%2C0%2C0%2C0%2C.06.13.53.53%2C0%2C0%2C0%2C.25%2C0h5a.49.49%2C0%2C0%2C0%2C.24%2C0%2C.14.14%2C0%2C0%2C0%2C0-.25.38.38%2C0%2C0%2C0-.21%2C0h-.87a.92.92%2C0%2C0%2C1-.39-.14.52.52%2C0%2C0%2C1-.2-.26%2C1.24%2C1.24%2C0%2C0%2C1-.09-.38%2C5.13%2C5.13%2C0%2C0%2C0-.06-.89%2C8.39%2C8.39%2C0%2C0%2C1%2C0-1.23V64.43a1.32%2C1.32%2C0%2C0%2C1%2C.16-.64.65.65%2C0%2C0%2C1%2C.48-.25l.26%2C0h.24a.34.34%2C0%2C0%2C0%2C.2%2C0%2C.16.16%2C0%2C0%2C0%2C.08-.15.14.14%2C0%2C0%2C0-.1-.11H14.83a.1.1%2C0%2C0%2C0-.1.11.15.15%2C0%2C0%2C0%2C.07.15.34.34%2C0%2C0%2C0%2C.2%2C0%2C1.71%2C1.71%2C0%2C0%2C1%2C.32%2C0l.3.06a.89.89%2C0%2C0%2C1%2C.31.15.5.5%2C0%2C0%2C1%2C.18.27%2C1.17%2C1.17%2C0%2C0%2C1%2C.09.45v6.4Zm10.59%2C4c.11.25.2.45.28.6a1%2C1%2C0%2C0%2C0%2C.21.3.33.33%2C0%2C0%2C0%2C.21.09.3.3%2C0%2C0%2C0%2C.22-.1%2C1.85%2C1.85%2C0%2C0%2C0%2C.25-.37c.09-.18.21-.42.35-.73l.52-1.15.76-1.71%2C1-2.19.61-1.33c.19-.39.36-.74.51-1.07l.46-1c.15-.33.3-.69.47-1.07s.28-.62.38-.81a2.49%2C2.49%2C0%2C0%2C1%2C.29-.43.8.8%2C0%2C0%2C1%2C.23-.22.83.83%2C0%2C0%2C1%2C.3-.14h.54a.35.35%2C0%2C0%2C0%2C.2%2C0%2C.11.11%2C0%2C0%2C0%2C.07-.12.14.14%2C0%2C0%2C0-.09-.13%2C1.13%2C1.13%2C0%2C0%2C0-.26%2C0H30.92a2.29%2C2.29%2C0%2C0%2C0-.37%2C0%2C.12.12%2C0%2C0%2C0-.12.13.16.16%2C0%2C0%2C0%2C.09.12.46.46%2C0%2C0%2C0%2C.2%2C0h.35a1.91%2C1.91%2C0%2C0%2C1%2C.33.06.4.4%2C0%2C0%2C1%2C.18.1.22.22%2C0%2C0%2C1%2C.06.19%2C1.22%2C1.22%2C0%2C0%2C1%2C0%2C.27%2C1.07%2C1.07%2C0%2C0%2C1-.11.33l-.27.7-.44%2C1.08-.54%2C1.33L29.69%2C69c-.2.49-.4%2C1-.58%2C1.41l-.52%2C1.23-.4.93h0l-2.88-7.39c-.11-.3-.21-.55-.28-.76a2.73%2C2.73%2C0%2C0%2C1-.1-.48.34.34%2C0%2C0%2C1%2C0-.2.4.4%2C0%2C0%2C1%2C.13-.13.73.73%2C0%2C0%2C1%2C.28-.1h.38a.32.32%2C0%2C0%2C0%2C.19%2C0%2C.13.13%2C0%2C0%2C0%2C.08-.12c0-.06%2C0-.1-.12-.13a1.41%2C1.41%2C0%2C0%2C0-.29%2C0H20.93a1.61%2C1.61%2C0%2C0%2C0-.31%2C0%2C.15.15%2C0%2C0%2C0-.12.13.24.24%2C0%2C0%2C0%2C0%2C.12.19.19%2C0%2C0%2C0%2C.16%2C0h.28a1.58%2C1.58%2C0%2C0%2C1%2C.38%2C0%2C1.55%2C1.55%2C0%2C0%2C1%2C.51.18%2C1.27%2C1.27%2C0%2C0%2C1%2C.38.35%2C3.83%2C3.83%2C0%2C0%2C1%2C.37.69l4.3%2C10.09Zm9.67-4v2.63a4.53%2C4.53%2C0%2C0%2C1%2C0%2C.88%2C2%2C2%2C0%2C0%2C1-.14.59.55.55%2C0%2C0%2C1-.37.29h-.6a.41.41%2C0%2C0%2C0-.22%2C0%2C.24.24%2C0%2C0%2C0%2C0%2C.12.13.13%2C0%2C0%2C0%2C.08.13.53.53%2C0%2C0%2C0%2C.25%2C0h7.27a4.17%2C4.17%2C0%2C0%2C0%2C.5%2C0%2C.54.54%2C0%2C0%2C0%2C.27-.11.71.71%2C0%2C0%2C0%2C.15-.3c0-.13.05-.25.07-.38s.06-.33.08-.52a2.2%2C2.2%2C0%2C0%2C1%2C.06-.53.89.89%2C0%2C0%2C0%2C0-.4%2C1.13%2C1.13%2C0%2C0%2C0%2C0-.26.15.15%2C0%2C0%2C0-.13-.13.14.14%2C0%2C0%2C0-.12.07.44.44%2C0%2C0%2C0-.07.19%2C2.21%2C2.21%2C0%2C0%2C1-.25.79%2C1.08%2C1.08%2C0%2C0%2C1-.49.43%2C2.13%2C2.13%2C0%2C0%2C1-.51.14%2C5.42%2C5.42%2C0%2C0%2C1-.58.06h-.52a6.23%2C6.23%2C0%2C0%2C1-1.36-.1%2C1.21%2C1.21%2C0%2C0%2C1-.72-.42%2C1.49%2C1.49%2C0%2C0%2C1-.23-.85V69.61a.24.24%2C0%2C0%2C1%2C0-.12H41.6a1.46%2C1.46%2C0%2C0%2C1%2C.51.12.77.77%2C0%2C0%2C1%2C.29.22.85.85%2C0%2C0%2C1%2C.15.3%2C1.71%2C1.71%2C0%2C0%2C1%2C0%2C.32v.29a.14.14%2C0%2C0%2C0%2C0%2C.09.13.13%2C0%2C0%2C0%2C.12%2C0%2C.14.14%2C0%2C0%2C0%2C.12-.06.44.44%2C0%2C0%2C0%2C.05-.15V69.36a4.23%2C4.23%2C0%2C0%2C1%2C.08-.66%2C1.25%2C1.25%2C0%2C0%2C1%2C0-.38v-.17A.13.13%2C0%2C0%2C0%2C43%2C68a.17.17%2C0%2C0%2C0-.1%2C0%2C.24.24%2C0%2C0%2C0-.11.06l-.16.15a.55.55%2C0%2C0%2C1-.31.18%2C4%2C4%2C0%2C0%2C1-.5.08H38.71a.24.24%2C0%2C0%2C1%2C0-.12V64.31a.24.24%2C0%2C0%2C1%2C0-.12h2.77a2.34%2C2.34%2C0%2C0%2C1%2C.64.12.85.85%2C0%2C0%2C1%2C.32.21.92.92%2C0%2C0%2C1%2C.16.27.58.58%2C0%2C0%2C1%2C.08.22v.22a.43.43%2C0%2C0%2C1%2C0%2C.16.43.43%2C0%2C0%2C0%2C0%2C.16h.11a.09.09%2C0%2C0%2C0%2C.1%2C0%2C.24.24%2C0%2C0%2C0%2C.06-.11v-.33a1.82%2C1.82%2C0%2C0%2C0%2C0-.33V63.66a1.8%2C1.8%2C0%2C0%2C1%2C.06-.32v-.16a.21.21%2C0%2C0%2C0%2C0-.11H34.52a.13.13%2C0%2C0%2C0%2C0%2C.25.41.41%2C0%2C0%2C0%2C.21%2C0h.72a1.57%2C1.57%2C0%2C0%2C1%2C.3.05%2C1.28%2C1.28%2C0%2C0%2C1%2C.42.17.61.61%2C0%2C0%2C1%2C.23.27%2C1.17%2C1.17%2C0%2C0%2C1%2C.09.45v6.4Zm10.78%2C0v2.63a3.79%2C3.79%2C0%2C0%2C1-.06.88%2C1.75%2C1.75%2C0%2C0%2C1-.14.59.5.5%2C0%2C0%2C1-.36.29h-.6a.41.41%2C0%2C0%2C0-.22%2C0%2C.16.16%2C0%2C0%2C0%2C0%2C.25.53.53%2C0%2C0%2C0%2C.25%2C0h4.75a.57.57%2C0%2C0%2C0%2C.26%2C0%2C.14.14%2C0%2C0%2C0%2C0-.25.2.2%2C0%2C0%2C0-.15%2C0h-.84a.93.93%2C0%2C0%2C1-.39-.15.67.67%2C0%2C0%2C1-.19-.3%2C2%2C2%2C0%2C0%2C1-.08-.43%2C5%2C5%2C0%2C0%2C0-.06-.88%2C7.86%2C7.86%2C0%2C0%2C1%2C0-1.19V70.61a.07.07%2C0%2C0%2C1%2C.1-.1h1.53a.43.43%2C0%2C0%2C1%2C.16%2C0%2C.24.24%2C0%2C0%2C1%2C.15.09l.25.33c.11.16.24.34.38.56l.48.67.5.69c.32.43.61.8.87%2C1.12a9.35%2C9.35%2C0%2C0%2C0%2C.74.8%2C3.57%2C3.57%2C0%2C0%2C0%2C.72.5%2C2.72%2C2.72%2C0%2C0%2C0%2C.47.19%2C2.93%2C2.93%2C0%2C0%2C0%2C.59.11h2.43a1%2C1%2C0%2C0%2C0%2C.25%2C0%2C.16.16%2C0%2C0%2C0%2C.08-.14.18.18%2C0%2C0%2C0%2C0-.12.22.22%2C0%2C0%2C0-.16%2C0H58.6l-.38-.1a2.88%2C2.88%2C0%2C0%2C1-.61-.3%2C5%2C5%2C0%2C0%2C1-.83-.69c-.51-.52-1.07-1.14-1.69-1.88s-1.3-1.57-2.06-2.5a10.23%2C10.23%2C0%2C0%2C0%2C1.36-1.27%2C4.85%2C4.85%2C0%2C0%2C0%2C.77-1.19%2C3%2C3%2C0%2C0%2C0%2C.24-1.19%2C2.59%2C2.59%2C0%2C0%2C0-.12-.78%2C3%2C3%2C0%2C0%2C0-.3-.65%2C3.14%2C3.14%2C0%2C0%2C0-.39-.51%2C3.09%2C3.09%2C0%2C0%2C0-.39-.33%2C3.61%2C3.61%2C0%2C0%2C0-1-.45%2C6.12%2C6.12%2C0%2C0%2C0-1.12-.2%2C10.46%2C10.46%2C0%2C0%2C0-1.12%2C0H46a1.31%2C1.31%2C0%2C0%2C0-.28%2C0%2C.12.12%2C0%2C0%2C0-.11.13.13.13%2C0%2C0%2C0%2C.09.12.41.41%2C0%2C0%2C0%2C.21%2C0h.38a1.35%2C1.35%2C0%2C0%2C1%2C.29%2C0%2C1.33%2C1.33%2C0%2C0%2C1%2C.43.17.58.58%2C0%2C0%2C1%2C.22.27%2C1.17%2C1.17%2C0%2C0%2C1%2C.09.45v6.32Zm2.17-6.54a.19.19%2C0%2C0%2C1%2C0-.15.2.2%2C0%2C0%2C1%2C.12-.08%2C2.81%2C2.81%2C0%2C0%2C1%2C.41%2C0h.6a3%2C3%2C0%2C0%2C1%2C.66.08%2C2.94%2C2.94%2C0%2C0%2C1%2C.69.28%2C2.14%2C2.14%2C0%2C0%2C1%2C.62.54%2C2.39%2C2.39%2C0%2C0%2C1%2C.45.83%2C4.12%2C4.12%2C0%2C0%2C1%2C0%2C2.36%2C2.41%2C2.41%2C0%2C0%2C1-.42.79%2C2.47%2C2.47%2C0%2C0%2C1-.52.5%2C1.18%2C1.18%2C0%2C0%2C1-.29.16%2C2.37%2C2.37%2C0%2C0%2C1-.36.09H50.2a3.53%2C3.53%2C0%2C0%2C1-.63-.13.23.23%2C0%2C0%2C1-.12-.1.31.31%2C0%2C0%2C1%2C0-.19v-5Z%22%2F%3E%3Cpath%20d%3D%22M69.88%2C74.71c.12.3.22.54.3.71a1.39%2C1.39%2C0%2C0%2C0%2C.22.37.29.29%2C0%2C0%2C0%2C.22.11.28.28%2C0%2C0%2C0%2C.24-.13%2C2%2C2%2C0%2C0%2C0%2C.26-.44q.15-.31.39-.87l.59-1.33c.24-.57.53-1.23.87-2l1.12-2.58c.21-.47.4-.9.58-1.28s.33-.74.48-1.07l.43-1c.13-.31.27-.62.41-.94l.43-1c.15-.35.33-.73.45-1a3.74%2C3.74%2C0%2C0%2C1%2C.35-.53%2C1.07%2C1.07%2C0%2C0%2C1%2C.27-.25%2C1.49%2C1.49%2C0%2C0%2C1%2C.36-.17l.33-.06h.49a.14.14%2C0%2C0%2C0%2C.08-.14c0-.07%2C0-.11-.11-.14H74.48a1.41%2C1.41%2C0%2C0%2C0-.41%2C0A.14.14%2C0%2C0%2C0%2C74%2C61a.17.17%2C0%2C0%2C0%2C0%2C.1.12.12%2C0%2C0%2C0%2C.1.13h.62a2.32%2C2.32%2C0%2C0%2C1%2C.38.07.32.32%2C0%2C0%2C1%2C.19.15.34.34%2C0%2C0%2C1%2C.07.22%2C1%2C1%2C0%2C0%2C1-.06.33%2C2.91%2C2.91%2C0%2C0%2C1-.12.39l-.31.83-.5%2C1.27c-.2.49-.4%2C1-.62%2C1.57s-.45%2C1.12-.68%2C1.69-.45%2C1.14-.67%2C1.68-.41%2C1-.59%2C1.48l-.45%2C1.14h-.08l-3.33-8.81c-.14-.35-.25-.65-.33-.91a1.94%2C1.94%2C0%2C0%2C1-.12-.58.89.89%2C0%2C0%2C1%2C0-.23.65.65%2C0%2C0%2C1%2C.15-.18.76.76%2C0%2C0%2C1%2C.32-.11%2C1.62%2C1.62%2C0%2C0%2C1%2C.44%2C0h.21a.14.14%2C0%2C0%2C0%2C.08-.14c0-.07%2C0-.11-.14-.14H63a1.15%2C1.15%2C0%2C0%2C0-.37%2C0%2C.14.14%2C0%2C0%2C0-.14.14.19.19%2C0%2C0%2C0%2C0%2C.13.28.28%2C0%2C0%2C0%2C.18%2C0%2C1.82%2C1.82%2C0%2C0%2C1%2C.33%2C0%2C3%2C3%2C0%2C0%2C1%2C.43.06%2C2.57%2C2.57%2C0%2C0%2C1%2C.6.23%2C1.54%2C1.54%2C0%2C0%2C1%2C.45.43%2C4.23%2C4.23%2C0%2C0%2C1%2C.42.82l4.89%2C11.85Zm14.24-3.24a.2.2%2C0%2C0%2C1%2C.11%2C0l.07.09%2C1.32%2C3.32a.28.28%2C0%2C0%2C1%2C0%2C.25.26.26%2C0%2C0%2C1-.15.12.25.25%2C0%2C0%2C0-.17%2C0%2C.24.24%2C0%2C0%2C0%2C0%2C.12.21.21%2C0%2C0%2C0%2C.13.1h4.13a.74.74%2C0%2C0%2C0%2C.21%2C0%2C.1.1%2C0%2C0%2C0%2C0-.11c0-.12-.08-.17-.23-.17H89a1.48%2C1.48%2C0%2C0%2C1-.27-.1%2C1.64%2C1.64%2C0%2C0%2C1-.33-.26%2C4%2C4%2C0%2C0%2C1-.4-.52%2C9.51%2C9.51%2C0%2C0%2C1-.46-.9c-.16-.36-.34-.79-.56-1.3s-.45-1-.7-1.64-.51-1.2-.78-1.81l-.77-1.81L84%2C65.23c-.21-.49-.4-.91-.54-1.26l-.31-.71A2.19%2C2.19%2C0%2C0%2C0%2C83%2C63a.35.35%2C0%2C0%2C0-.15-.17.35.35%2C0%2C0%2C0-.24-.06.29.29%2C0%2C0%2C0-.2.16%2C1.83%2C1.83%2C0%2C0%2C0-.26.5L77.67%2C73.77a5.93%2C5.93%2C0%2C0%2C1-.34.72%2C1.59%2C1.59%2C0%2C0%2C1-.44.49%2C1.4%2C1.4%2C0%2C0%2C1-.63.25h-.51a.2.2%2C0%2C0%2C0-.15%2C0%2C.24.24%2C0%2C0%2C0%2C0%2C.12.15.15%2C0%2C0%2C0%2C.07.14%2C1%2C1%2C0%2C0%2C0%2C.24%2C0h3.88a.67.67%2C0%2C0%2C0%2C.2%2C0%2C.13.13%2C0%2C0%2C0%2C.07-.14.13.13%2C0%2C0%2C0%2C0-.12.26.26%2C0%2C0%2C0-.21%2C0h-.42a.85.85%2C0%2C0%2C1-.54-.13.4.4%2C0%2C0%2C1-.14-.34%2C3%2C3%2C0%2C0%2C1%2C.06-.42%2C4.06%2C4.06%2C0%2C0%2C1%2C.19-.59l.91-2.21a.15.15%2C0%2C0%2C1%2C.06-.09.17.17%2C0%2C0%2C1%2C.1%2C0Zm-3.69-.86a.09.09%2C0%2C0%2C1-.07%2C0%2C.14.14%2C0%2C0%2C1%2C0-.09L82%2C66.35v-.1h.06v.1l1.61%2C4.19a.11.11%2C0%2C0%2C1%2C0%2C.08H80.43ZM93.89%2C68V64.48a1.32%2C1.32%2C0%2C0%2C1%2C.16-.64.65.65%2C0%2C0%2C1%2C.48-.25l.33-.05h.33a.49.49%2C0%2C0%2C0%2C.24%2C0%2C.13.13%2C0%2C0%2C0%2C.08-.12.13.13%2C0%2C0%2C0-.08-.13%2C1.31%2C1.31%2C0%2C0%2C0-.28%2C0H90.43a1.31%2C1.31%2C0%2C0%2C0-.28%2C0%2C.14.14%2C0%2C0%2C0-.09.13c0%2C.11.1.17.29.17h.31l.26.05a1.28%2C1.28%2C0%2C0%2C1%2C.42.17.67.67%2C0%2C0%2C1%2C.23.27%2C1.42%2C1.42%2C0%2C0%2C1%2C.08.45v9a3.79%2C3.79%2C0%2C0%2C1-.06.88%2C1.75%2C1.75%2C0%2C0%2C1-.14.59.5.5%2C0%2C0%2C1-.36.29h-.6a.41.41%2C0%2C0%2C0-.22%2C0%2C.16.16%2C0%2C0%2C0%2C0%2C.25.53.53%2C0%2C0%2C0%2C.25%2C0H98c.22%2C0%2C.43%2C0%2C.65%2C0a.54.54%2C0%2C0%2C0%2C.3-.13.72.72%2C0%2C0%2C0%2C.13-.28%2C2.73%2C2.73%2C0%2C0%2C0%2C.1-.48c0-.19.06-.38.08-.58a4.66%2C4.66%2C0%2C0%2C0%2C0-.53%2C1.61%2C1.61%2C0%2C0%2C0%2C0-.31%2C1.13%2C1.13%2C0%2C0%2C0%2C0-.26.11.11%2C0%2C0%2C0-.12-.11.13.13%2C0%2C0%2C0-.14.07.55.55%2C0%2C0%2C0-.06.18%2C1.37%2C1.37%2C0%2C0%2C1-.08.35%2C2.67%2C2.67%2C0%2C0%2C1-.14.36%2C2.83%2C2.83%2C0%2C0%2C1-.2.28%2C1.42%2C1.42%2C0%2C0%2C1-.51.32%2C2.41%2C2.41%2C0%2C0%2C1-.66.12%2C5.75%2C5.75%2C0%2C0%2C1-.83%2C0H95.45a3.67%2C3.67%2C0%2C0%2C1-.74-.11%2C1.16%2C1.16%2C0%2C0%2C1-.42-.2%2C1%2C1%2C0%2C0%2C1-.26-.57%2C8.77%2C8.77%2C0%2C0%2C1-.1-1.14V67.82Zm10.71%2C0V64.48a1.32%2C1.32%2C0%2C0%2C1%2C.16-.64.65.65%2C0%2C0%2C1%2C.48-.25l.33-.05h.33a.46.46%2C0%2C0%2C0%2C.23%2C0%2C.13.13%2C0%2C0%2C0%2C.08-.12.14.14%2C0%2C0%2C0-.09-.13%2C1.31%2C1.31%2C0%2C0%2C0-.28%2C0H101a1.31%2C1.31%2C0%2C0%2C0-.28%2C0%2C.14.14%2C0%2C0%2C0-.09.13c0%2C.11.1.17.29.17h.31a1%2C1%2C0%2C0%2C1%2C.25.05%2C1.33%2C1.33%2C0%2C0%2C1%2C.43.17.58.58%2C0%2C0%2C1%2C.22.27%2C1.17%2C1.17%2C0%2C0%2C1%2C.09.45v9a3.79%2C3.79%2C0%2C0%2C1-.06.88%2C1.75%2C1.75%2C0%2C0%2C1-.14.59.5.5%2C0%2C0%2C1-.36.29h-.6a.41.41%2C0%2C0%2C0-.22%2C0%2C.16.16%2C0%2C0%2C0-.06.13.16.16%2C0%2C0%2C0%2C.06.12.53.53%2C0%2C0%2C0%2C.25%2C0h7.56q.33%2C0%2C.66%2C0a.46.46%2C0%2C0%2C0%2C.29-.13.62.62%2C0%2C0%2C0%2C.14-.28%2C2.73%2C2.73%2C0%2C0%2C0%2C.1-.48c0-.19.06-.38.08-.58a2.73%2C2.73%2C0%2C0%2C1%2C0-.53%2C1.61%2C1.61%2C0%2C0%2C0%2C0-.31%2C1.13%2C1.13%2C0%2C0%2C0%2C0-.26.11.11%2C0%2C0%2C0-.12-.11c-.06%2C0-.12%2C0-.14.07a.55.55%2C0%2C0%2C0-.06.18%2C1.37%2C1.37%2C0%2C0%2C1-.08.35%2C2.75%2C2.75%2C0%2C0%2C1-.15.36%2C1.73%2C1.73%2C0%2C0%2C1-.19.28%2C1.42%2C1.42%2C0%2C0%2C1-.51.32%2C2.41%2C2.41%2C0%2C0%2C1-.66.12%2C5.75%2C5.75%2C0%2C0%2C1-.83%2C0h-1.11a3.67%2C3.67%2C0%2C0%2C1-.74-.11%2C1%2C1%2C0%2C0%2C1-.42-.2%2C1%2C1%2C0%2C0%2C1-.26-.57%2C8.77%2C8.77%2C0%2C0%2C1-.1-1.14V67.82ZM113%2C70.88v2.63a3.79%2C3.79%2C0%2C0%2C1-.06.88%2C1.75%2C1.75%2C0%2C0%2C1-.14.59.5.5%2C0%2C0%2C1-.36.29h-.6a.41.41%2C0%2C0%2C0-.22%2C0%2C.17.17%2C0%2C0%2C0-.06.12.14.14%2C0%2C0%2C0%2C.09.13.49.49%2C0%2C0%2C0%2C.24%2C0h7.28a4%2C4%2C0%2C0%2C0%2C.49%2C0%2C.57.57%2C0%2C0%2C0%2C.28-.11.64.64%2C0%2C0%2C0%2C.14-.3%2C2.33%2C2.33%2C0%2C0%2C0%2C.08-.38c0-.16%2C0-.33.07-.52a2.2%2C2.2%2C0%2C0%2C1%2C.06-.53%2C2.67%2C2.67%2C0%2C0%2C0%2C0-.4.57.57%2C0%2C0%2C0%2C0-.26.15.15%2C0%2C0%2C0-.13-.13.15.15%2C0%2C0%2C0-.13.07.6.6%2C0%2C0%2C0-.06.19%2C2.23%2C2.23%2C0%2C0%2C1-.26.79%2C1.05%2C1.05%2C0%2C0%2C1-.48.43%2C2.35%2C2.35%2C0%2C0%2C1-.52.14%2C5.51%2C5.51%2C0%2C0%2C1-.57.06h-.52a6.28%2C6.28%2C0%2C0%2C1-1.37-.1%2C1.19%2C1.19%2C0%2C0%2C1-.71-.42%2C1.49%2C1.49%2C0%2C0%2C1-.23-.85V69.61a.24.24%2C0%2C0%2C1%2C0-.12h2.72a1.46%2C1.46%2C0%2C0%2C1%2C.51.12.84.84%2C0%2C0%2C1%2C.3.22.69.69%2C0%2C0%2C1%2C.14.3%2C1.71%2C1.71%2C0%2C0%2C1%2C0%2C.32v.29a.14.14%2C0%2C0%2C0%2C0%2C.09h.12a.11.11%2C0%2C0%2C0%2C.11-.06.38.38%2C0%2C0%2C0%2C0-.15.43.43%2C0%2C0%2C0%2C0-.16v-1.1a4.23%2C4.23%2C0%2C0%2C1%2C.08-.66%2C2.36%2C2.36%2C0%2C0%2C0%2C0-.38v-.17a.24.24%2C0%2C0%2C0%2C0-.12.17.17%2C0%2C0%2C0-.1%2C0%2C.14.14%2C0%2C0%2C0-.11.06l-.16.15a.57.57%2C0%2C0%2C1-.32.18%2C2.74%2C2.74%2C0%2C0%2C1-.5.08h-2.79a.24.24%2C0%2C0%2C1%2C0-.12V64.31a.24.24%2C0%2C0%2C1%2C0-.12h2.76a2.34%2C2.34%2C0%2C0%2C1%2C.64.12.81.81%2C0%2C0%2C1%2C.33.21.92.92%2C0%2C0%2C1%2C.16.27.57.57%2C0%2C0%2C1%2C.07.22.81.81%2C0%2C0%2C1%2C0%2C.22.43.43%2C0%2C0%2C1%2C0%2C.16.43.43%2C0%2C0%2C0%2C0%2C.16h.11a.11.11%2C0%2C0%2C0%2C.11%2C0l.06-.11V63.66a1.52%2C1.52%2C0%2C0%2C1%2C.06-.32.43.43%2C0%2C0%2C0%2C0-.16.21.21%2C0%2C0%2C0%2C0-.11h-8.49a.15.15%2C0%2C0%2C0-.1.13.13.13%2C0%2C0%2C0%2C.08.12.54.54%2C0%2C0%2C0%2C.21%2C0h.39a1.35%2C1.35%2C0%2C0%2C1%2C.29.05%2C1.61%2C1.61%2C0%2C0%2C1%2C.43.17.64.64%2C0%2C0%2C1%2C.22.27%2C1.17%2C1.17%2C0%2C0%2C1%2C.09.45v6.4Z%22%2F%3E%3Cpath%20d%3D%22M126.3%2C72.7v1.64a1.35%2C1.35%2C0%2C0%2C1-.14.59.59.59%2C0%2C0%2C1-.38.29h-.6a.38.38%2C0%2C0%2C0-.21%2C0%2C.16.16%2C0%2C0%2C0%2C0%2C.26h5.21a.61.61%2C0%2C0%2C0%2C.27%2C0%2C.13.13%2C0%2C0%2C0%2C.1-.13.15.15%2C0%2C0%2C0-.07-.12.41.41%2C0%2C0%2C0-.22%2C0h-.85a.78.78%2C0%2C0%2C1-.53-.29%2C1.12%2C1.12%2C0%2C0%2C1-.17-.59v-3.5a4.86%2C4.86%2C0%2C0%2C1%2C0-.54%2C2.69%2C2.69%2C0%2C0%2C1%2C.17-.57c.06-.13.16-.32.32-.59s.34-.59.56-1l.69-1.12c.24-.39.48-.76.71-1.11l.62-.94a6%2C6%2C0%2C0%2C1%2C.42-.57%2C3.65%2C3.65%2C0%2C0%2C1%2C.31-.36%2C1.55%2C1.55%2C0%2C0%2C1%2C.27-.24l.31-.18.4-.14a1.93%2C1.93%2C0%2C0%2C1%2C.34%2C0%2C.48.48%2C0%2C0%2C0%2C.24-.06.14.14%2C0%2C0%2C0%2C.09-.13.12.12%2C0%2C0%2C0-.08-.11h-3.94a.15.15%2C0%2C0%2C0-.07.13.14.14%2C0%2C0%2C0%2C.09.13l.22.06a.46.46%2C0%2C0%2C1%2C.29.15.35.35%2C0%2C0%2C1%2C.08.22%2C1.22%2C1.22%2C0%2C0%2C1-.07.38%2C2.26%2C2.26%2C0%2C0%2C1-.19.49%2C2%2C2%2C0%2C0%2C1-.26.48l-.46.8-.56%2C1-.56%2C1q-.27.45-.45.78l-.25.42-.29-.48-.5-.86-.62-1.06-.61-1-.51-.88c-.15-.24-.25-.41-.3-.5a3%2C3%2C0%2C0%2C1-.16-.31%2C1%2C1%2C0%2C0%2C1%2C0-.25.23.23%2C0%2C0%2C1%2C.06-.16.56.56%2C0%2C0%2C1%2C.17-.09l.3-.09a.11.11%2C0%2C0%2C0%2C.09-.12.17.17%2C0%2C0%2C0-.07-.13h-4.64a.13.13%2C0%2C0%2C0-.08.13.13.13%2C0%2C0%2C0%2C.08.12.34.34%2C0%2C0%2C0%2C.17%2C0%2C1.13%2C1.13%2C0%2C0%2C1%2C.36.06%2C1.94%2C1.94%2C0%2C0%2C1%2C.36.15%2C1.92%2C1.92%2C0%2C0%2C1%2C.52.42c.18.2.37.45.59.75l.42.63c.18.28.38.59.61.93l.67%2C1c.23.35.44.68.63%2C1l.49.77a2.88%2C2.88%2C0%2C0%2C1%2C.22.38%2C4%2C4%2C0%2C0%2C1%2C.21.47%2C3%2C3%2C0%2C0%2C1%2C.13.52%2C4.6%2C4.6%2C0%2C0%2C1%2C0%2C.74V72.7Z%22%2F%3E%3C%2Fg%3E%3C%2Fg%3E%3C%2Fsvg%3E",
      "logo_config": {
        "type": "svg",
        "variant": "dark",
        "url": null
      },
      "logo_colors": null,
      "favicon_url": "https://book.gke1-west3.wsf-prod-1.wstack.net/favicon.ico"
    }
  }